django_invisible_recaptcha_admin/__init__.py
django_invisible_recaptcha_admin/admin.py
django_invisible_recaptcha_admin/forms.py
django_invisible_recaptcha_admin/models.py
django_invisible_recaptcha_admin/tests.py
django_invisible_recaptcha_admin/views.py
django_invisible_recaptcha_admin/migrations/__init__.py
django_invisible_recaptcha_admin/templates/admin/login.html
django_invisible_recaptcha_admin-1.0.0.dist-info/DESCRIPTION.rst
django_invisible_recaptcha_admin-1.0.0.dist-info/METADATA
django_invisible_recaptcha_admin-1.0.0.dist-info/RECORD
django_invisible_recaptcha_admin-1.0.0.dist-info/WHEEL
django_invisible_recaptcha_admin-1.0.0.dist-info/metadata.json
django_invisible_recaptcha_admin-1.0.0.dist-info/top_level.txt
