Metadata-Version: 2.0
Name: django-invisible-recaptcha-admin
Version: 1.0.0
Summary: Invisible captcha in administrative login.
Home-page: https://github.com/ricardochaves/django_invisible_recaptcha_admin
Author: Ricardo Baltazar Chaves
Author-email: ricardobchaves6@gmail.com
License: BSD
Keywords: django,recaptcha,field
Platform: UNKNOWN
Classifier: Development Status :: 3 - Alpha
Classifier: Environment :: Web Environment
Classifier: Framework :: Django
Classifier: Framework :: Django :: 2.0
Classifier: Intended Audience :: Developers
Classifier: License :: OSI Approved :: BSD License
Classifier: Operating System :: OS Independent
Classifier: Programming Language :: Python
Classifier: Programming Language :: Python :: 3
Classifier: Programming Language :: Python :: 3.4
Classifier: Programming Language :: Python :: 3.5
Classifier: Programming Language :: Python :: 3.6
Classifier: Topic :: Internet :: WWW/HTTP
Classifier: Topic :: Internet :: WWW/HTTP :: Dynamic Content
Classifier: Topic :: Internet :: WWW/HTTP :: WSGI
Classifier: Topic :: Software Development :: Libraries :: Application Frameworks
Classifier: Topic :: Software Development :: Libraries :: Python Modules
Classifier: Natural Language :: Portuguese (Brazilian)
Requires-Dist: django-nocaptcha-recaptcha-inv
